mcp_calculator_demo/__init__.py
mcp_calculator_demo/server.py
mcp_calculator_demo-0.4.1.dist-info/METADATA
mcp_calculator_demo-0.4.1.dist-info/WHEEL
mcp_calculator_demo-0.4.1.dist-info/entry_points.txt
mcp_calculator_demo-0.4.1.dist-info/RECORD
