Metadata-Version: 2.4
Name: mcp-calculator-demo
Version: 0.4.1
Summary: A Model Context Protocol server providing calculator functionality with auto-configuration
Project-URL: Homepage, https://github.com/yourusername/mcp-calculator-demo
Project-URL: Repository, https://github.com/yourusername/mcp-calculator-demo
Project-URL: Issues, https://github.com/yourusername/mcp-calculator-demo/issues
Author-email: Your Name <your.email@example.com>
License: MIT
Keywords: auto-config,calculator,mcp,model-context-protocol
Classifier: Development Status :: 3 - Alpha
Classifier: Intended Audience :: Developers
Classifier: License :: OSI Approved :: MIT License
Classifier: Programming Language :: Python :: 3
Classifier: Programming Language :: Python :: 3.11
Classifier: Programming Language :: Python :: 3.12
Classifier: Programming Language :: Python :: 3.13
Requires-Python: >=3.11
Requires-Dist: fastmcp>=2.10.0
